crowd.py
crowdpy-1.3.0.dist-info/LICENSE.md
crowdpy-1.3.0.dist-info/METADATA
crowdpy-1.3.0.dist-info/NOTICE.md
crowdpy-1.3.0.dist-info/WHEEL
crowdpy-1.3.0.dist-info/top_level.txt
crowdpy-1.3.0.dist-info/RECORD
