Metadata-Version: 2.1
Name: crowdpy
Version: 1.3.0
Summary: A Python library for Atlassian Crowd REST API
Home-page: https://github.com/yoobato/crowdpy
Author: Daeyeol Ryu
Author-email: yoobato@gmail.com
License: Apache-2.0
Keywords: atlassian,crowd
Classifier: Development Status :: 4 - Beta
Classifier: Intended Audience :: Developers
Classifier: License :: OSI Approved :: Apache Software License
Classifier: Operating System :: OS Independent
Classifier: Programming Language :: Python
Classifier: Programming Language :: Python :: 3
Classifier: Programming Language :: Python :: 3 :: Only
Classifier: Programming Language :: Python :: 3.9
Classifier: Programming Language :: Python :: 3.10
Classifier: Topic :: Software Development :: Libraries
Classifier: Topic :: Software Development :: Libraries :: Python Modules
Classifier: Topic :: System :: Systems Administration :: Authentication/Directory
Requires-Python: >=3.9
License-File: LICENSE.md
License-File: NOTICE.md
Requires-Dist: requests
